git_fame-3.1.1.dist-info/licenses/LICENCE
gitfame/__init__.py
gitfame/__main__.py
gitfame/_dist_ver.py
gitfame/_gitfame.py
gitfame/_utils.py
gitfame/git-fame.1
git_fame-3.1.1.dist-info/METADATA
git_fame-3.1.1.dist-info/WHEEL
git_fame-3.1.1.dist-info/entry_points.txt
git_fame-3.1.1.dist-info/top_level.txt
git_fame-3.1.1.dist-info/RECORD
